orray/__init__.py
orray/constructions.py
orray/oa.py
orray-0.1.0.dist-info/METADATA
orray-0.1.0.dist-info/WHEEL
orray-0.1.0.dist-info/licenses/LICENSE
orray-0.1.0.dist-info/RECORD
