Metadata-Version: 2.4
Name: orray
Version: 0.1.0
Summary: Python package for efficient instantiation of large orthogonal arrays.
Project-URL: repository, https://github.com/peter-koepernik/orray
Author-email: Peter Koepernik <peter@koepernik.net>, Thomas Coxon <t.coxon2@lboro.ac.uk>
License:                                  Apache License
License-File: LICENSE
Keywords: combinatorics,jax,orray,orthogonal-arrays
Classifier: Development Status :: 3 - Alpha
Classifier: Intended Audience :: Developers
Classifier: Intended Audience :: Financial and Insurance Industry
Classifier: Intended Audience :: Information Technology
Classifier: Intended Audience :: Science/Research
Classifier: License :: OSI Approved :: Apache Software License
Classifier: Natural Language :: English
Classifier: Programming Language :: Python :: 3
Classifier: Programming Language :: Python :: 3.10
Classifier: Programming Language :: Python :: 3.11
Classifier: Programming Language :: Python :: 3.12
Classifier: Programming Language :: Python :: 3.13
Classifier: Topic :: Scientific/Engineering :: Information Analysis
Classifier: Topic :: Scientific/Engineering :: Mathematics
Requires-Python: >=3.10
Requires-Dist: equinox
Requires-Dist: galois
Requires-Dist: jax
Requires-Dist: jaxtyping
